hf_pipeline_viz/__init__.py
hf_pipeline_viz/main.py
hf_pipeline_viz-0.1.0.dist-info/licenses/LICENSE
hf_pipeline_viz-0.1.0.dist-info/METADATA
hf_pipeline_viz-0.1.0.dist-info/WHEEL
hf_pipeline_viz-0.1.0.dist-info/top_level.txt
hf_pipeline_viz-0.1.0.dist-info/RECORD
