Metadata-Version: 2.4
Name: hf_pipeline_viz
Version: 0.1.0
Summary: Attention heat-map helper for Hugging Face text-generation pipelines
Author: Vaibhav Gupta
Author-email: vaibhavguptaq8@gmail.com
License: MIT
License-File: LICENSE
Requires-Dist: transformers
Requires-Dist: torch
Requires-Dist: numpy
Requires-Dist: matplotlib
Dynamic: author
Dynamic: author-email
Dynamic: description
Dynamic: description-content-type
Dynamic: license
Dynamic: license-file
Dynamic: requires-dist
Dynamic: summary
